micro_notif/__init__.py
micro_notif/v1/__init__.py
micro_notif/v1/clients.py
micro_notif/v1/connection.py
micro_notif/v1/types.py
micro_notif/v1/utils.py
micro_notif_client-0.2.1.dist-info/LICENSE
micro_notif_client-0.2.1.dist-info/METADATA
micro_notif_client-0.2.1.dist-info/WHEEL
micro_notif_client-0.2.1.dist-info/top_level.txt
micro_notif_client-0.2.1.dist-info/RECORD
