Metadata-Version: 2.1
Name: micro-notif-client
Version: 0.2.1
Summary: A minimal python client for micro-notif
Author: Alirzea Jafari
Author-email: alirzeaja1384@gmail.com
License: MIT
Classifier: Programming Language :: Python :: 3
Requires-Python: >=3.9
License-File: LICENSE
Requires-Dist: aio-pika >=9.3.0
